twitch/__init__.py
twitch/twitch.py
twitch_MagicaFreak-1.0.0.dist-info/LICENSE
twitch_MagicaFreak-1.0.0.dist-info/METADATA
twitch_MagicaFreak-1.0.0.dist-info/WHEEL
twitch_MagicaFreak-1.0.0.dist-info/top_level.txt
twitch_MagicaFreak-1.0.0.dist-info/RECORD
