Metadata-Version: 2.1
Name: twitch-MagicaFreak
Version: 1.0.0
Summary: A Twitch Wrapper for Python 3.6 or higher for the new Twitch API
Home-page: https://github.com/MagicaFreak/Python-TwitchAPI
Author: MagicaFreak
Author-email: magicafreak97@gmail.com
License: UNKNOWN
Platform: UNKNOWN
Classifier: Programming Language :: Python :: 3
Classifier: License :: OSI Approved :: MIT License
Classifier: Operating System :: OS Independent
Requires-Python: >=3.6
